navigation_api/__init__.py
navigation_api/data_classes.py
navigation_api/location.py
navigation_api/navigation.py
navigation_api-0.0.1a0.dist-info/LICENSE
navigation_api-0.0.1a0.dist-info/METADATA
navigation_api-0.0.1a0.dist-info/WHEEL
navigation_api-0.0.1a0.dist-info/top_level.txt
navigation_api-0.0.1a0.dist-info/RECORD
